pytest_logscanner-0.9.3.dist-info/METADATA
pytest_logscanner-0.9.3.dist-info/WHEEL
pytest_logscanner-0.9.3.dist-info/entry_points.txt
pytest_logscanner/__init__.py
pytest_logscanner/py.typed
pytest_logscanner/pytest_logscanner.py
pytest_logscanner-0.9.3.dist-info/RECORD
