Metadata-Version: 2.1
Name: pytest-logscanner
Version: 0.9.3
Summary: Pytest plugin for logscanner (A logger for python logging outputting to easily viewable (and filterable) html files. Good for people not grep savey, and color higlighting and quickly changing filters might even bye useful for commandline wizards.)
Keywords: logging,viewer
Author-Email: Malte Vesper <malte.vesper@gmx.net>
License: MIT
Classifier: Development Status :: 4 - Beta
Classifier: Programming Language :: Python :: 3
Classifier: Programming Language :: Python :: 3.12
Classifier: License :: OSI Approved :: MIT License
Classifier: Operating System :: OS Independent
Classifier: Typing :: Typed
Classifier: Framework :: Pytest
Project-URL: Documentation, https://maltevesper.github.io/logscanner/
Project-URL: Repository, https://github.com/maltevesper/logscanner
Project-URL: Changelog, https://github.com/maltevesper/logscanner/blob/main/CHANGELOG.md
Requires-Python: >=3.12
Requires-Dist: logscanner>=0.9.3
Requires-Dist: pytest>=8.2.2
